CHANGELOG
LICENSE
MANIFEST.in
README.md
buku.1
buku.py
pyproject.toml
requirements.txt
auto-completion/bash/buku-completion.bash
auto-completion/fish/buku.fish
auto-completion/zsh/_buku
buku.egg-info/PKG-INFO
buku.egg-info/SOURCES.txt
buku.egg-info/dependency_links.txt
buku.egg-info/entry_points.txt
buku.egg-info/requires.txt
buku.egg-info/top_level.txt
bukuserver/__init__.py
bukuserver/__main__.py
bukuserver/api.py
bukuserver/filters.py
bukuserver/forms.py
bukuserver/response.py
bukuserver/server.py
bukuserver/util.py
bukuserver/views.py
bukuserver/middleware/__init__.py
bukuserver/middleware/flask_reverse_proxy_fix.py
bukuserver/static/bukuserver/favicon.svg
bukuserver/static/bukuserver/css/bookmark.css
bukuserver/static/bukuserver/css/list.css
bukuserver/static/bukuserver/css/modal.css
bukuserver/static/bukuserver/js/Chart.js
bukuserver/static/bukuserver/js/bookmark.js
bukuserver/static/bukuserver/js/buku_filter.js
bukuserver/static/bukuserver/js/filters_fix.js
bukuserver/static/bukuserver/js/last_page.js
bukuserver/static/bukuserver/js/order_filter.js
bukuserver/templates/bukuserver/bookmark_create.html
bukuserver/templates/bukuserver/bookmark_create_modal.html
bukuserver/templates/bukuserver/bookmark_details.html
bukuserver/templates/bukuserver/bookmark_details_modal.html
bukuserver/templates/bukuserver/bookmark_edit.html
bukuserver/templates/bukuserver/bookmark_edit_modal.html
bukuserver/templates/bukuserver/bookmarklet.url
bukuserver/templates/bukuserver/bookmarks_list.html
bukuserver/templates/bukuserver/home.html
bukuserver/templates/bukuserver/lib.html
bukuserver/templates/bukuserver/statistic.html
bukuserver/templates/bukuserver/tag_edit.html
bukuserver/templates/bukuserver/tags_list.html
bukuserver/translations/__init__.py
bukuserver/translations/__main__.py
tests/__init__.py
tests/test_BukuCrypt.py
tests/test_ExtendedArgumentParser.py
tests/test_buku.py
tests/test_bukuDb.py
tests/test_cli.py
tests/test_import_firefox_json.py
tests/test_requirements.py
tests/test_server.py
tests/test_views.py
tests/util.py
tests/test_bukuDb/25491522_res.yaml
tests/test_bukuDb/25491522_res_nopt.yaml
tests/test_bukuDb/Bookmarks
