Metadata-Version: 2.4
Name: buku
Version: 5.1
Summary: Bookmark manager like a text-based mini-web.
Author-email: Arun Prakash Jana <engineerarun@gmail.com>
License-Expression: GPL-3.0-or-later
Project-URL: Homepage, https://github.com/jarun/buku
Project-URL: Documentation, https://buku.readthedocs.io/en/latest
Project-URL: Funding, https://github.com/sponsors/jarun
Project-URL: Source, https://github.com/jarun/buku
Project-URL: Tracker, https://github.com/jarun/buku/issues
Keywords: cli,bookmarks,tag,utility
Classifier: Development Status :: 5 - Production/Stable
Classifier: Environment :: Console
Classifier: Intended Audience :: Developers
Classifier: Intended Audience :: End Users/Desktop
Classifier: Natural Language :: English
Classifier: Operating System :: OS Independent
Classifier: Programming Language :: Python :: 3
Classifier: Programming Language :: Python :: 3 :: Only
Classifier: Programming Language :: Python :: 3.10
Classifier: Programming Language :: Python :: 3.11
Classifier: Programming Language :: Python :: 3.12
Classifier: Programming Language :: Python :: 3.13
Classifier: Programming Language :: Python :: 3.14
Classifier: Topic :: Internet :: WWW/HTTP :: Indexing/Search
Classifier: Topic :: Utilities
Requires-Python: >=3.10
License-File: LICENSE
Requires-Dist: beautifulsoup4>=4.4.1
Requires-Dist: certifi
Requires-Dist: cryptography>=1.2.3
Requires-Dist: html5lib>=1.0.1
Requires-Dist: urllib3<3,>=1.23
Requires-Dist: pyreadline3; sys_platform == "win32"
Requires-Dist: colorama>=0.4.6; sys_platform == "win32"
Provides-Extra: server
Requires-Dist: arrow>=1.2.2; extra == "server"
Requires-Dist: Flask-Admin>=2.0.0; extra == "server"
Requires-Dist: flask-paginate>=2022.1.8; extra == "server"
Requires-Dist: Flask-WTF>=1.0.1; extra == "server"
Requires-Dist: Flask>=2.2.2; extra == "server"
Requires-Dist: Jinja2>=3; extra == "server"
Requires-Dist: flasgger; extra == "server"
Provides-Extra: locales
Requires-Dist: Flask-Admin[translation]; extra == "locales"
Dynamic: license-file
